Metadata-Version: 2.1
Name: servitor
Version: 0.0.1
Summary: Terminal
Home-page: https://github.com/mirmik/servitor
Author: mirmik
Author-email: netricks@protonmail.ru
License: MIT
Keywords: testing,terminal
Platform: UNKNOWN
